bb_utils/__init__.py
bb_utils/crypto.py
bb_utils/env.py
bb_utils/migrations.py
bb_utils/aiohttp/__init__.py
bb_utils/aiohttp/headers.py
bb_utils/aiohttp/paginator.py
bb_utils/aiohttp/responses.py
bb_utils-0.0.11.dist-info/METADATA
bb_utils-0.0.11.dist-info/RECORD
bb_utils-0.0.11.dist-info/WHEEL
bb_utils-0.0.11.dist-info/top_level.txt
